paas_service/__init__.py
paas_service/admin.py
paas_service/apps.py
paas_service/auth/__init__.py
paas_service/auth/backends.py
paas_service/auth/decorator.py
paas_service/auth/middleware.py
paas_service/base_vendor.py
paas_service/constants.py
paas_service/fields.py
paas_service/management/__init__.py
paas_service/management/commands/__init__.py
paas_service/management/commands/clean_deleting_instances.py
paas_service/migrations/0001_initial.py
paas_service/migrations/0002_serviceinstance_need_to_delete.py
paas_service/migrations/0003_auto_20200102_2209.py
paas_service/migrations/0004_serviceinstanceconfig.py
paas_service/migrations/0005_auto_20210202_1055.py
paas_service/migrations/0006_auto_20210223_0948.py
paas_service/migrations/0007_auto_20220426_0225.py
paas_service/migrations/0008_auto_20220426_0429.py
paas_service/migrations/0009_alter_plan_unique_together_plan_tenant_id_and_more.py
paas_service/migrations/__init__.py
paas_service/mixins.py
paas_service/models.py
paas_service/serializers.py
paas_service/tasks.py
paas_service/urls.py
paas_service/utils.py
paas_service/views.py
paas_service-2.0.3.dist-info/METADATA
paas_service-2.0.3.dist-info/WHEEL
paas_service-2.0.3.dist-info/RECORD
