Metadata-Version: 2.1
Name: paas-service
Version: 2.0.3
Summary: A Django application for developing BK-PaaS add-on services.
License: MIT
Author: blueking
Author-email: blueking@tencent.com
Requires-Python: >=3.8,<3.12
Classifier: License :: OSI Approved :: MIT License
Classifier: Programming Language :: Python :: 3
Classifier: Programming Language :: Python :: 3.8
Classifier: Programming Language :: Python :: 3.9
Classifier: Programming Language :: Python :: 3.10
Classifier: Programming Language :: Python :: 3.11
Requires-Dist: blue-krill (>=2.0.7,<3.0.0)
Requires-Dist: django (>=4.2.16,<5.0.0)
Requires-Dist: django-translated-fields
Requires-Dist: djangorestframework (>=3.15.2,<4.0.0)
Requires-Dist: jsonfield
Requires-Dist: pydantic (==2.9.2)
Requires-Dist: pyjwt (>=2.4.0,<3.0.0)
